hanspitools/__init__.py
hanspitools/freq.py
hanspitools/mani.py
hanspitools-0.0.10.dist-info/LICENSE
hanspitools-0.0.10.dist-info/METADATA
hanspitools-0.0.10.dist-info/WHEEL
hanspitools-0.0.10.dist-info/top_level.txt
hanspitools-0.0.10.dist-info/RECORD
